{
  "prefix": "progress",
  "tokens": {
    "color": {
      "track": {
        "background": "{semantic.color.background.secondary}"
      },
      "fill": {
        "info": "{semantic.color.status.info}",
        "success": "{semantic.color.status.success}",
        "warning": "{semantic.color.status.warning}",
        "danger": "{semantic.color.status.danger}"
      },
      "text": {
        "default": "{semantic.color.foreground.secondary}"
      }
    },
    "size": {
      "linear": {
        "sm": {
          "height": "{core.spacing.size.02}",
          "radius": "{core.shape.radius.full}"
        },
        "md": {
          "height": "{core.spacing.size.03}",
          "radius": "{core.shape.radius.full}"
        },
        "lg": {
          "height": "{core.spacing.size.04}",
          "radius": "{core.shape.radius.full}"
        }
      },
      "circular": {
        "sm": {
          "size": {
            "value": 32,
            "unit": "px"
          },
          "strokeWidth": {
            "value": 2,
            "unit": "px"
          }
        },
        "md": {
          "size": {
            "value": 40,
            "unit": "px"
          },
          "strokeWidth": {
            "value": 3,
            "unit": "px"
          }
        },
        "lg": {
          "size": {
            "value": 48,
            "unit": "px"
          },
          "strokeWidth": {
            "value": 4,
            "unit": "px"
          }
        }
      }
    },
    "typography": {
      "value": {
        "fontSize": "{semantic.typography.caption.01}",
        "fontWeight": "{semantic.typography.fontWeight.medium}"
      }
    },
    "motion": {
      "duration": {
        "indeterminate": "1.5s"
      },
      "easing": {
        "indeterminate": "ease-in-out"
      }
    },
    "spacing": {
      "gap": "{core.spacing.size.02}"
    }
  }
}
